graphtec_reader/__init__.py
graphtec_reader/__main__.py
graphtec_reader/helper_function.py
modbus_configuretools/__init__.py
modbus_configuretools/derived_modbus_wrapper.py
modbus_configuretools/helper_function.py
modbus_configuretools/modbus_wrapper.py
modbus_configuretools/temperature_sensor.py
temperature_data_analysis/__init__.py
temperature_data_analysis/data_wrapper.py
temperature_data_analysis/helper_function.py
temperature_data_analysis/plot_wrapper.py
temperature_sensor_reader_xzf8971-2.0.0.dist-info/LICENSE
temperature_sensor_reader_xzf8971-2.0.0.dist-info/METADATA
temperature_sensor_reader_xzf8971-2.0.0.dist-info/WHEEL
temperature_sensor_reader_xzf8971-2.0.0.dist-info/top_level.txt
temperature_sensor_reader_xzf8971-2.0.0.dist-info/RECORD
