Metadata-Version: 2.1
Name: temperature-sensor-reader-xzf8971
Version: 2.0.0
Summary: A package to read/write registers on a temperature sensor with python.
Author-email: Zifeng <zifeng.xu@foxmail.com>
Project-URL: Homepage, https://github.com/xzf89718/temperature_sensor_reader
Project-URL: Bug Tracker, https://github.com/xzf89718/temperature_sensor_reader/issues
Classifier: Programming Language :: Python :: 3
Classifier: License :: OSI Approved :: MIT License
Classifier: Operating System :: OS Independent
Requires-Python: >=3.7
License-File: LICENSE
Requires-Dist: numpy
Requires-Dist: pyserial
Requires-Dist: pyserial-asyncio
Requires-Dist: pymodbus
Requires-Dist: pandas
Requires-Dist: bs4
Requires-Dist: custom-logger-xzf8971
